bsplines2d/__init__.py
bsplines2d/_class01_Mesh2D.py
bsplines2d/_class01_checks_1d.py
bsplines2d/_class01_checks_2d_polar.py
bsplines2d/_class01_checks_2d_rect.py
bsplines2d/_class01_checks_2d_tri.py
bsplines2d/_class01_cropping.py
bsplines2d/_class01_outline.py
bsplines2d/_class01_plot.py
bsplines2d/_class01_sample.py
bsplines2d/_class01_sample3d.py
bsplines2d/_class01_select.py
bsplines2d/_class01_slice3d.py
bsplines2d/_class02_BSplines2D.py
bsplines2d/_class02_bsplines_1d.py
bsplines2d/_class02_bsplines_operators_1d.py
bsplines2d/_class02_bsplines_operators_rect.py
bsplines2d/_class02_bsplines_polar.py
bsplines2d/_class02_bsplines_rect.py
bsplines2d/_class02_bsplines_tri.py
bsplines2d/_class02_checks.py
bsplines2d/_class02_compute.py
bsplines2d/_class02_contours.py
bsplines2d/_class02_interpolate.py
bsplines2d/_class02_interpolate_all.py
bsplines2d/_class02_line_tracing.py
bsplines2d/_class02_operators.py
bsplines2d/_class02_plot.py
bsplines2d/_class02_plot_as_profile2d.py
bsplines2d/_class02_plot_as_profile2d_compare.py
bsplines2d/_class02_plot_operators.py
bsplines2d/_class03_Bins.py
bsplines2d/_class03_binning.py
bsplines2d/_class03_checks.py
bsplines2d/_class11_plot.py
bsplines2d/_generic_check.py
bsplines2d/_generic_mesh.py
bsplines2d/_saveload.py
bsplines2d/_utils_bsplines.py
bsplines2d/_utils_bsplines_operators.py
bsplines2d/_version.py
bsplines2d/tests/__init__.py
bsplines2d/tests/prepublish.py
bsplines2d/tests/test_01_Mesh2D.py
bsplines2d/tests/test_input.py
bsplines2d/tests/test_data/WEST_Poly.npz
bsplines2d/tests/test_data/WEST_trimesh.npz
bsplines2d/tests/test_data/__init__.py
bsplines2d/tests/test_data/mesh_triangular_WEST_eq.txt
bsplines2d/tests/test_data/trimesh_quad.npz
bsplines2d-0.0.29.dist-info/licenses/LICENSE.txt
bsplines2d-0.0.29.dist-info/METADATA
bsplines2d-0.0.29.dist-info/WHEEL
bsplines2d-0.0.29.dist-info/top_level.txt
bsplines2d-0.0.29.dist-info/RECORD
