Metadata-Version: 2.4
Name: bsplines2d
Version: 0.0.29
Summary: Generic handler for 1d and 1d bsplines meshes, uses datastock
Author-email: Didier VEZINET <didier.vezinet@gmail.com>
Maintainer-email: Didier VEZINET <didier.vezinet@gmail.com>
License: MIT
Project-URL: Homepage, https://github.com/ToFuProject/bsplines2d
Project-URL: Issues, https://github.com/ToFuProject/bsplines2d/issues
Keywords: data,analysis,interactive,bsplines,Collection,mesh
Classifier: Development Status :: 5 - Production/Stable
Classifier: Intended Audience :: Science/Research
Classifier: Programming Language :: Python :: 3
Classifier: Programming Language :: Python :: 3.6
Classifier: Programming Language :: Python :: 3.7
Classifier: Programming Language :: Python :: 3.8
Classifier: Programming Language :: Python :: 3.9
Classifier: Programming Language :: Python :: 3.10
Classifier: Programming Language :: Python :: 3.11
Classifier: Natural Language :: English
Requires-Python: >=3.8
License-File: LICENSE.txt
Requires-Dist: contourpy
Requires-Dist: datastock>=0.0.55
Provides-Extra: linting
Requires-Dist: ruff; extra == "linting"
Provides-Extra: formatting
Requires-Dist: ruff; extra == "formatting"
Dynamic: license-file
